token_parser/__init__.py
token_parser/parsers.py
token_parser/utils.py
token_parser/examples/__init__.py
token_parser/examples/date_add.py
token_parser/examples/guid.py
token_parser/examples/inc_and_dec.py
token_parser/examples/int_and_float.py
token_parser/examples/now_and_utcnow.py
token_parser/examples/parse_json_template.py
token_parser/tests/__init__.py
token_parser/tests/parsers_tests.py
token_parser-0.0.8.dist-info/METADATA
token_parser-0.0.8.dist-info/WHEEL
token_parser-0.0.8.dist-info/top_level.txt
token_parser-0.0.8.dist-info/RECORD
